ml_lib/__init__.py
ml_lib/print_correlation/__init__.py
ml_lib/print_correlation/print_correlation.py
ml_lib/print_scatter/__init__.py
ml_lib/print_scatter/print_scatter.py
ml_lib/train_levels/__init__.py
ml_lib/train_levels/train_levels.py
ml_lib/train_stack_model/__init__.py
ml_lib/train_stack_model/train_stack_model.py
gobuubstackmodel-0.9.dist-info/METADATA
gobuubstackmodel-0.9.dist-info/WHEEL
gobuubstackmodel-0.9.dist-info/top_level.txt
gobuubstackmodel-0.9.dist-info/RECORD
