Metadata-Version: 2.1
Name: gobuubstackmodel
Version: 0.9
Summary: Personal Python lib for used on EDA's and train ML models
Home-page: https://github.com/Gobuub/Gobuub-Stack-Model-Lib
Author: Enrique Revuelta Garcia
Author-email: enrique.revuelta@enriquerevueltagarcia.com
License: MIT License
Platform: UNKNOWN
Requires-Dist: setuptools (~=61.2.0)
Requires-Dist: pandas (~=1.4.2)
Requires-Dist: numpy (~=1.22.4)
Requires-Dist: seaborn (~=0.11.2)
Requires-Dist: matplotlib (~=3.5.2)
Requires-Dist: tqdm (~=4.64.0)
Requires-Dist: sklearn (~=0.0)
Requires-Dist: scikit-learn (~=1.1.1)
